automate_office/__init__.py
automate_office/automate_ppt/Charts.py
automate_office/automate_ppt/MyPPTCreator.py
automate_office/automate_ppt/__init__.py
automate_office/automate_ppt/helper_func.py
automate_office/automate_ppt/ppt_enums.py
automate_ppt-0.1.0.dist-info/LICENSE
automate_ppt-0.1.0.dist-info/METADATA
automate_ppt-0.1.0.dist-info/WHEEL
automate_ppt-0.1.0.dist-info/top_level.txt
automate_ppt-0.1.0.dist-info/RECORD
