Metadata-Version: 2.1
Name: automate-ppt
Version: 0.1.0
Summary: Offic自动化工具-自用，在原有包的基础上二次开发
Home-page: 
Author: Sun Meng
Author-email: clivesun@163.com
Classifier: Development Status :: 3 - Alpha
Classifier: Intended Audience :: Developers
Classifier: Topic :: Software Development :: Build Tools
Classifier: License :: OSI Approved :: MIT License
Classifier: Programming Language :: Python :: 3
Classifier: Programming Language :: Python :: 3.10
License-File: LICENSE
Requires-Dist: python-docx ==1.1.0
Requires-Dist: python-pptx ==0.6.23
